sigmap/__init__.py
sigmap/const.py
sigmap/feature.py
sigmap/setup.py
sigmap/sigmapred.py
sigmap/model/__init__.py
sigmap/model/svc_model_sigma70
sigmap-1.1.2.dist-info/METADATA
sigmap-1.1.2.dist-info/WHEEL
sigmap-1.1.2.dist-info/licenses/LICENSE
sigmap-1.1.2.dist-info/RECORD
