Metadata-Version: 2.4
Name: sigmap
Version: 1.1.2
Summary: SigmaP: Python package for predicting sigma70 promoter in Escherichia coli K-12
Project-URL: Homepage, https://github.com/Goosang-Yu/sigmap
Project-URL: Repository, https://github.com/Goosang-Yu/sigmap
Project-URL: Source, https://github.com/Goosang-Yu/sigmap
Project-URL: Tracker, https://github.com/Goosang-Yu/sigmap/issues
Author-email: Goosang Yu <gsyu93@gmail.com>
License-File: LICENSE
Keywords: analysis,bacteria,bioinformatics,genetics,machine-learning,promoter,python
Classifier: Intended Audience :: Developers
Classifier: Intended Audience :: Science/Research
Classifier: Operating System :: MacOS :: MacOS X
Classifier: Operating System :: Microsoft :: Windows
Classifier: Operating System :: POSIX
Classifier: Operating System :: Unix
Classifier: Programming Language :: Python
Classifier: Programming Language :: Python :: 3 :: Only
Classifier: Programming Language :: Python :: 3.7
Classifier: Programming Language :: Python :: 3.8
Classifier: Programming Language :: Python :: 3.9
Classifier: Programming Language :: Python :: 3.10
Classifier: Topic :: Software Development
Classifier: Topic :: Software Development :: Libraries
Classifier: Topic :: Software Development :: Libraries :: Application Frameworks
Classifier: Topic :: Software Development :: Libraries :: Python Modules
Requires-Python: >=3.7
Requires-Dist: pandas
Requires-Dist: scikit-learn
